action/__init__.py
action/action.py
updatedpip-1.0.dist-info/METADATA
updatedpip-1.0.dist-info/RECORD
updatedpip-1.0.dist-info/WHEEL
updatedpip-1.0.dist-info/top_level.txt
