Metadata-Version: 2.1
Name: updatedpip
Version: 1.0
Summary: Example pip package
Home-page: UNKNOWN
Author: VikdaBeast
Author-email: UNKNOWN
License: UNKNOWN
Platform: UNKNOWN
